setup.py
tools/__init__.py
tools/analysis_dependency.py
tools/analysis_tools.py
tools/brain_hole_diff.py
tools/fix_git_author.py
tools/fix_git_changed_file_newlines.py
tools/inline_style.py
tools/mk_unittest.py
ycyc/__init__.py
ycyc.egg-info/PKG-INFO
ycyc.egg-info/SOURCES.txt
ycyc.egg-info/dependency_links.txt
ycyc.egg-info/requires.txt
ycyc.egg-info/top_level.txt
ycyc/base/__init__.py
ycyc/base/adapter.py
ycyc/base/allowfail.py
ycyc/base/calctools.py
ycyc/base/contextutils.py
ycyc/base/decoratorutils.py
ycyc/base/filetools.py
ycyc/base/funcutils.py
ycyc/base/iterutils.py
ycyc/base/lazyutils.py
ycyc/base/logutils.py
ycyc/base/marker.py
ycyc/base/resources.py
ycyc/base/shelltools.py
ycyc/base/txtutils.py
ycyc/base/typeutils.py
ycyc/contribs/__init__.py
ycyc/contribs/tail_call_optimized.py
ycyc/debug/__init__.py
ycyc/debug/decorators.py
ycyc/frameworks/__init__.py
ycyc/frameworks/events/__init__.py
ycyc/frameworks/events/base.py
ycyc/frameworks/events/subscribers.py
ycyc/frameworks/spider/__init__.py
ycyc/frameworks/spider/utils.py
ycyc/libs/__init__.py
ycyc/libs/algorithms/__init__.py
ycyc/libs/algorithms/hashlib/__init__.py
ycyc/libs/algorithms/hashlib/simhash.py
ycyc/libs/algorithms/sequences/__init__.py
ycyc/libs/algorithms/sequences/alignment.py
ycyc/libs/mathutils/__init__.py
ycyc/libs/mathutils/matrix.py
ycyc/libs/process/__init__.py
ycyc/libs/process/deamon.py
ycyc/libs/rediskit/__init__.py
ycyc/libs/rediskit/base.py
ycyc/libs/rediskit/hash_dict.py
ycyc/libs/statelib/__init__.py
ycyc/libs/statelib/state.py
ycyc/libs/task/__init__.py
ycyc/libs/task/asynckit.py
ycyc/libs/txtgen/__init__.py
ycyc/shortcuts/__init__.py
ycyc/shortcuts/contextmanagers.py
ycyc/shortcuts/decorators.py
ycyc/tests/__init__.py
ycyc/tests/base/__init__.py
ycyc/tests/base/test_adapter.py
ycyc/tests/base/test_allowfail.py
ycyc/tests/base/test_calctools.py
ycyc/tests/base/test_contextutils.py
ycyc/tests/base/test_decoratorutils.py
ycyc/tests/base/test_filetools.py
ycyc/tests/base/test_funcutils.py
ycyc/tests/base/test_iterutils.py
ycyc/tests/base/test_lazyutils.py
ycyc/tests/base/test_logutils.py
ycyc/tests/base/test_marker.py
