Metadata-Version: 1.1
Name: ycyc
Version: 0.1.11.7
Summary: a library by LYC
Home-page: UNKNOWN
Author: Liu Yicong
Author-email: imyikong@gmail.com
License: BSD
Platform: UNKNOWN
Classifier: Development Status :: 3 - Alpha
Classifier: License :: OSI Approved :: BSD License
Classifier: Natural Language :: English
Classifier: Programming Language :: Python :: 2
Classifier: Programming Language :: Python :: 2.6
Classifier: Programming Language :: Python :: 2.7
